mathcalcusuit/__init__.py
mathcalcusuit/mathcalcusuit.py
mathcalcusuit-0.1.0.dist-info/License
mathcalcusuit-0.1.0.dist-info/METADATA
mathcalcusuit-0.1.0.dist-info/WHEEL
mathcalcusuit-0.1.0.dist-info/top_level.txt
mathcalcusuit-0.1.0.dist-info/RECORD
