Metadata-Version: 2.1
Name: mathcalcusuit
Version: 0.1.0
Summary: A simple package for basic math operations including prime checking, Fibonacci, GCD, LCM, and factorials
Author: Md. Ismiel Hossen Abir
Author-email: ismielabir1971@gmail.com
Classifier: Programming Language :: Python :: 3
Classifier: License :: OSI Approved :: MIT License
Classifier: Operating System :: OS Independent
License-File: License
